simon/__init__.py
simon/simon.py
simon/stats.py
simon_mac-0.1.1.data/scripts/simon
simon_mac-0.1.1.dist-info/DESCRIPTION.rst
simon_mac-0.1.1.dist-info/METADATA
simon_mac-0.1.1.dist-info/RECORD
simon_mac-0.1.1.dist-info/WHEEL
simon_mac-0.1.1.dist-info/metadata.json
simon_mac-0.1.1.dist-info/top_level.txt
