Metadata-Version: 2.0
Name: simon-mac
Version: 0.1.1
Summary: Simple menubar system monitor for macOS.
Home-page: http://pypi.python.org/pypi/simon_mac/
Author: Ray Chen
Author-email: ray@half0wl.com
License: MIT
Platform: UNKNOWN
Classifier: Development Status :: 3 - Alpha
Classifier: Environment :: MacOS X
Classifier: Environment :: MacOS X :: Cocoa
Classifier: Intended Audience :: Developers
Classifier: Intended Audience :: End Users/Desktop
Classifier: License :: OSI Approved :: MIT License
Classifier: Operating System :: MacOS
Classifier: Programming Language :: Python :: 2.7
Classifier: Programming Language :: Python :: 3
Classifier: Programming Language :: Python :: 3.6
Classifier: Topic :: System :: Monitoring
Classifier: Topic :: Utilities
Requires-Dist: psutil (>=5.2.0)
Requires-Dist: pyobjc-core (>=3.2.1)
Requires-Dist: pyobjc-framework-Cocoa (>=3.2.1)
